{
  "name": "st-nucleo-f401re-gcc",
  "version": "0.0.8",
  "description": "WARNING: DEPRECATED EXPERIMENTAL TARGET, DO NOT USE.",
  "licenses": [
    {
      "url": "https://spdx.org/licenses/Apache-2.0",
      "type": "Apache-2.0"
    }
  ],
  "keywords": [
    "mbed-target:nucleo_f401re",
    "nucleo_f401re",
    "f401",
    "nucleo",
    "gcc"
  ],
  "similarTo": [
    "nucleo-f401re",
    "f401re",
    "f401",
    "nucleo",
    "stm32f401ret6",
    "stm32f401re",
    "stm32f401",
    "stm32f4",
    "stm32",
    "st",
    "cortex-m4",
    "armv7-m",
    "arm",
    "gcc",
    "mbed"
  ],
  "toolchain": "CMake/toolchain.cmake",
  "scripts": {
    "debug": [
      "valinor",
      "--target",
      "ST_NUCLEO_F401RE",
      "$program"
    ],
    "test": [
      "mbed_test_wrapper",
      "--target",
      "ST_NUCLEO_F401RE",
      "$program"
    ]
  }
}
